{
    "ticker": "TLT",
    "display": "5-min",
    "periods": 100,
    "interval": "5min",
    "current_price": 86.63,
    "focus_price": 86.63,
    "quote_time_eastern": "2026-04-23 05:15 PM",
    "quote_timezone": "EDT",
    "resistance_1": {
        "price": 86.75,
        "diff": 0.12,
        "touches": 13,
        "range": [
            86.69,
            86.8
        ]
    },
    "resistance_2": {
        "price": 86.92,
        "diff": 0.28,
        "touches": 39,
        "range": [
            86.82,
            86.98
        ]
    },
    "support_1": {
        "price": 86.55,
        "diff": 0.08,
        "touches": 38,
        "range": [
            86.43,
            86.61
        ]
    },
    "support_2": {
        "price": 86.29,
        "diff": 0.35,
        "touches": 10,
        "range": [
            86.24,
            86.32
        ]
    },
    "upper_resistances": [
        {
            "price": 86.75,
            "diff": 0.12,
            "touches": 13,
            "range": [
                86.69,
                86.8
            ]
        },
        {
            "price": 86.92,
            "diff": 0.28,
            "touches": 39,
            "range": [
                86.82,
                86.98
            ]
        }
    ],
    "lower_supports": [
        {
            "price": 86.55,
            "diff": 0.08,
            "touches": 38,
            "range": [
                86.43,
                86.61
            ]
        },
        {
            "price": 86.29,
            "diff": 0.35,
            "touches": 10,
            "range": [
                86.24,
                86.32
            ]
        }
    ],
    "channels": [
        {
            "name": "current",
            "lower": 86.55,
            "upper": 86.75,
            "width": 0.2,
            "location": "inside"
        },
        {
            "name": "above_resistance",
            "lower": 86.75,
            "upper": 86.92,
            "width": 0.17,
            "location": "potential_upside_channel"
        },
        {
            "name": "below_support",
            "lower": 86.29,
            "upper": 86.55,
            "width": 0.26,
            "location": "potential_downside_channel"
        }
    ],
    "previous_day": {
        "date": null,
        "high": null,
        "low": null,
        "open": null,
        "close": null,
        "volume": null
    },
    "recent_extremes": {
        "window_bars": 20,
        "recent_high": 86.66,
        "recent_low": 86.49
    },
    "attempts": {
        "failed_up_today": 1,
        "failed_down_today": 1,
        "rule_of_three_block_up": false,
        "rule_of_three_block_down": false
    },
    "probabilities": {
        "up": 47.9,
        "down": 52.1,
        "bias": "neutral",
        "confidence": "low"
    },
    "score_drivers": [
        {
            "factor": "channel_position",
            "value": 0.42,
            "impact": -2.07
        },
        {
            "factor": "failed_up_attempts",
            "value": 1,
            "impact": -7.5
        },
        {
            "factor": "failed_down_attempts",
            "value": 1,
            "impact": 7.5
        }
    ],
    "history": [
        {
            "time": "2026-04-23T12:45:00+00:00",
            "open": 86.7,
            "high": 86.8,
            "low": 86.68,
            "close": 86.7,
            "volume": 102799,
            "ma20": null,
            "rsi14": null,
            "macd": null,
            "macd_signal": null,
            "macd_hist": null
        },
        {
            "time": "2026-04-23T12:50:00+00:00",
            "open": 86.79,
            "high": 86.79,
            "low": 86.73,
            "close": 86.79,
            "volume": 44416.4333,
            "ma20": null,
            "rsi14": null,
            "macd": null,
            "macd_signal": null,
            "macd_hist": null
        },
        {
            "time": "2026-04-23T12:55:00+00:00",
            "open": 86.77,
            "high": 86.78,
            "low": 86.72,
            "close": 86.77,
            "volume": 17189.265033,
            "ma20": null,
            "rsi14": null,
            "macd": null,
            "macd_signal": null,
            "macd_hist": null
        },
        {
            "time": "2026-04-23T13:00:00+00:00",
            "open": 86.8005,
            "high": 86.8203,
            "low": 86.7799,
            "close": 86.8005,
            "volume": 2131.099915,
            "ma20": null,
            "rsi14": null,
            "macd": null,
            "macd_signal": null,
            "macd_hist": null
        },
        {
            "time": "2026-04-23T13:05:00+00:00",
            "open": 86.78,
            "high": 86.79,
            "low": 86.77,
            "close": 86.78,
            "volume": 1669,
            "ma20": null,
            "rsi14": null,
            "macd": null,
            "macd_signal": null,
            "macd_hist": null
        },
        {
            "time": "2026-04-23T13:10:00+00:00",
            "open": 86.73,
            "high": 86.785,
            "low": 86.68,
            "close": 86.73,
            "volume": 37413,
            "ma20": null,
            "rsi14": null,
            "macd": null,
            "macd_signal": null,
            "macd_hist": null
        },
        {
            "time": "2026-04-23T13:15:00+00:00",
            "open": 86.78,
            "high": 86.79,
            "low": 86.77,
            "close": 86.78,
            "volume": 5947,
            "ma20": null,
            "rsi14": null,
            "macd": null,
            "macd_signal": null,
            "macd_hist": null
        },
        {
            "time": "2026-04-23T13:20:00+00:00",
            "open": 86.82,
            "high": 86.84,
            "low": 86.795,
            "close": 86.82,
            "volume": 4249.02311,
            "ma20": null,
            "rsi14": null,
            "macd": null,
            "macd_signal": null,
            "macd_hist": null
        },
        {
            "time": "2026-04-23T13:25:00+00:00",
            "open": 86.84,
            "high": 86.84,
            "low": 86.8,
            "close": 86.84,
            "volume": 19330,
            "ma20": null,
            "rsi14": null,
            "macd": null,
            "macd_signal": null,
            "macd_hist": null
        },
        {
            "time": "2026-04-23T13:30:00+00:00",
            "open": 86.8434,
            "high": 86.895,
            "low": 86.8203,
            "close": 86.8434,
            "volume": 303805.32195400004,
            "ma20": null,
            "rsi14": null,
            "macd": null,
            "macd_signal": null,
            "macd_hist": null
        },
        {
            "time": "2026-04-23T13:35:00+00:00",
            "open": 86.8899,
            "high": 86.89,
            "low": 86.835,
            "close": 86.8899,
            "volume": 83802.43181000001,
            "ma20": null,
            "rsi14": null,
            "macd": null,
            "macd_signal": null,
            "macd_hist": null
        },
        {
            "time": "2026-04-23T13:40:00+00:00",
            "open": 86.87,
            "high": 86.915,
            "low": 86.86,
            "close": 86.87,
            "volume": 85701.211988,
            "ma20": null,
            "rsi14": null,
            "macd": null,
            "macd_signal": null,
            "macd_hist": null
        },
        {
            "time": "2026-04-23T13:45:00+00:00",
            "open": 86.895,
            "high": 86.915,
            "low": 86.81,
            "close": 86.895,
            "volume": 185577.30333400003,
            "ma20": null,
            "rsi14": null,
            "macd": null,
            "macd_signal": null,
            "macd_hist": null
        },
        {
            "time": "2026-04-23T13:50:00+00:00",
            "open": 86.9099,
            "high": 86.935,
            "low": 86.88,
            "close": 86.9099,
            "volume": 140719.852934,
            "ma20": null,
            "rsi14": null,
            "macd": null,
            "macd_signal": null,
            "macd_hist": null
        },
        {
            "time": "2026-04-23T13:55:00+00:00",
            "open": 86.915,
            "high": 86.95,
            "low": 86.8912,
            "close": 86.915,
            "volume": 40738.227344,
            "ma20": null,
            "rsi14": 74.66727856815089,
            "macd": null,
            "macd_signal": null,
            "macd_hist": null
        },
        {
            "time": "2026-04-23T14:00:00+00:00",
            "open": 86.915,
            "high": 86.92,
            "low": 86.845,
            "close": 86.915,
            "volume": 66307.383877,
            "ma20": null,
            "rsi14": 74.66727856815089,
            "macd": null,
            "macd_signal": null,
            "macd_hist": null
        },
        {
            "time": "2026-04-23T14:05:00+00:00",
            "open": 86.935,
            "high": 86.96,
            "low": 86.915,
            "close": 86.935,
            "volume": 167485.99877000003,
            "ma20": null,
            "rsi14": 75.94746436131412,
            "macd": null,
            "macd_signal": null,
            "macd_hist": null
        },
        {
            "time": "2026-04-23T14:10:00+00:00",
            "open": 86.9697,
            "high": 86.97,
            "low": 86.93,
            "close": 86.9697,
            "volume": 58249.73976,
            "ma20": null,
            "rsi14": 78.02262244916652,
            "macd": null,
            "macd_signal": null,
            "macd_hist": null
        },
        {
            "time": "2026-04-23T14:15:00+00:00",
            "open": 86.9702,
            "high": 86.985,
            "low": 86.94,
            "close": 86.9702,
            "volume": 181083.633401,
            "ma20": null,
            "rsi14": 78.05200641146475,
            "macd": null,
            "macd_signal": null,
            "macd_hist": null
        },
        {
            "time": "2026-04-23T14:20:00+00:00",
            "open": 86.975,
            "high": 86.98,
            "low": 86.945,
            "close": 86.975,
            "volume": 44646.600363,
            "ma20": 86.85493,
            "rsi14": 78.35124889664246,
            "macd": null,
            "macd_signal": null,
            "macd_hist": null
        },
        {
            "time": "2026-04-23T14:25:00+00:00",
            "open": 86.965,
            "high": 87,
            "low": 86.96,
            "close": 86.965,
            "volume": 131099.782344,
            "ma20": 86.86818000000001,
            "rsi14": 76.02566453084037,
            "macd": null,
            "macd_signal": null,
            "macd_hist": null
        },
        {
            "time": "2026-04-23T14:30:00+00:00",
            "open": 86.915,
            "high": 86.995,
            "low": 86.915,
            "close": 86.915,
            "volume": 89785.570703,
            "ma20": 86.87443,
            "rsi14": 65.54933493836228,
            "macd": null,
            "macd_signal": null,
            "macd_hist": null
        },
        {
            "time": "2026-04-23T14:35:00+00:00",
            "open": 86.925,
            "high": 86.95,
            "low": 86.9,
            "close": 86.925,
            "volume": 94340.32101000001,
            "ma20": 86.88218,
            "rsi14": 66.54235711751105,
            "macd": null,
            "macd_signal": null,
            "macd_hist": null
        },
        {
            "time": "2026-04-23T14:40:00+00:00",
            "open": 86.96,
            "high": 86.965,
            "low": 86.9,
            "close": 86.96,
            "volume": 61160.721103,
            "ma20": 86.89015500000001,
            "rsi14": 69.82116885526744,
            "macd": null,
            "macd_signal": null,
            "macd_hist": null
        },
        {
            "time": "2026-04-23T14:45:00+00:00",
            "open": 86.995,
            "high": 87,
            "low": 86.95,
            "close": 86.995,
            "volume": 107567.77089300001,
            "ma20": 86.900905,
            "rsi14": 72.70211309919253,
            "macd": null,
            "macd_signal": null,
            "macd_hist": null
        },
        {
            "time": "2026-04-23T14:50:00+00:00",
            "open": 87.005,
            "high": 87.01,
            "low": 86.98,
            "close": 87.005,
            "volume": 64230.222411999996,
            "ma20": 86.91465500000001,
            "rsi14": 73.48105544215127,
            "macd": 0.06660043295289597,
            "macd_signal": null,
            "macd_hist": null
        },
        {
            "time": "2026-04-23T14:55:00+00:00",
            "open": 86.99,
            "high": 87.0099,
            "low": 86.97,
            "close": 86.99,
            "volume": 77175.082107,
            "ma20": 86.92515499999999,
            "rsi14": 70.24320671580045,
            "macd": 0.06517945904693079,
            "macd_signal": null,
            "macd_hist": null
        },
        {
            "time": "2026-04-23T15:00:00+00:00",
            "open": 86.99,
            "high": 87.01,
            "low": 86.955,
            "close": 86.99,
            "volume": 63351.068887,
            "ma20": 86.933655,
            "rsi14": 70.24320671580045,
            "macd": 0.06332337454456649,
            "macd_signal": null,
            "macd_hist": null
        },
        {
            "time": "2026-04-23T15:05:00+00:00",
            "open": 86.965,
            "high": 86.99,
            "low": 86.95,
            "close": 86.965,
            "volume": 25666.173124,
            "ma20": 86.939905,
            "rsi14": 64.72999279748564,
            "macd": 0.05915324139263589,
            "macd_signal": null,
            "macd_hist": null
        },
        {
            "time": "2026-04-23T15:10:00+00:00",
            "open": 86.98,
            "high": 86.9901,
            "low": 86.96,
            "close": 86.98,
            "volume": 47692.92835,
            "ma20": 86.946735,
            "rsi14": 66.43237497216592,
            "macd": 0.056408513237784064,
            "macd_signal": null,
            "macd_hist": null
        },
        {
            "time": "2026-04-23T15:15:00+00:00",
            "open": 87.01,
            "high": 87.0169,
            "low": 86.96,
            "close": 87.01,
            "volume": 140105.953267,
            "ma20": 86.95274,
            "rsi14": 69.59344035314636,
            "macd": 0.05600841552971758,
            "macd_signal": null,
            "macd_hist": null
        },
        {
            "time": "2026-04-23T15:20:00+00:00",
            "open": 87.015,
            "high": 87.035,
            "low": 86.995,
            "close": 87.015,
            "volume": 92156.32229299999,
            "ma20": 86.95999,
            "rsi14": 70.09883931233288,
            "macd": 0.055455536521620274,
            "macd_signal": null,
            "macd_hist": null
        },
        {
            "time": "2026-04-23T15:25:00+00:00",
            "open": 87.0051,
            "high": 87.04,
            "low": 87,
            "close": 87.0051,
            "volume": 52072.132769,
            "ma20": 86.965495,
            "rsi14": 67.69944278292319,
            "macd": 0.05360065369167444,
            "macd_signal": null,
            "macd_hist": null
        },
        {
            "time": "2026-04-23T15:30:00+00:00",
            "open": 86.9774,
            "high": 87,
            "low": 86.9507,
            "close": 86.9774,
            "volume": 205028.608484,
            "ma20": 86.96887000000001,
            "rsi14": 61.369853322359226,
            "macd": 0.04932687764323873,
            "macd_signal": 0.058339611617896026,
            "macd_hist": -0.009012733974657294
        },
        {
            "time": "2026-04-23T15:35:00+00:00",
            "open": 86.95,
            "high": 86.98,
            "low": 86.935,
            "close": 86.95,
            "volume": 168258.244034,
            "ma20": 86.97062,
            "rsi14": 55.81122681040449,
            "macd": 0.04323059295977316,
            "macd_signal": 0.055317807886271456,
            "macd_hist": -0.012087214926498294
        },
        {
            "time": "2026-04-23T15:40:00+00:00",
            "open": 86.915,
            "high": 86.9703,
            "low": 86.915,
            "close": 86.915,
            "volume": 74118.281541,
            "ma20": 86.97062,
            "rsi14": 49.627668675220576,
            "macd": 0.03516962241907606,
            "macd_signal": 0.051288170792832384,
            "macd_hist": -0.01611854837375632
        },
        {
            "time": "2026-04-23T15:45:00+00:00",
            "open": 86.925,
            "high": 86.925,
            "low": 86.83,
            "close": 86.925,
            "volume": 207858.819143,
            "ma20": 86.97012,
            "rsi14": 51.28827625626889,
            "macd": 0.029250974588961753,
            "macd_signal": 0.04688073155205826,
            "macd_hist": -0.01762975696309651
        },
        {
            "time": "2026-04-23T15:50:00+00:00",
            "open": 86.88,
            "high": 86.925,
            "low": 86.855,
            "close": 86.88,
            "volume": 114898.448897,
            "ma20": 86.96563499999999,
            "rsi14": 44.22312322421494,
            "macd": 0.020690769313645774,
            "macd_signal": 0.04164273910437577,
            "macd_hist": -0.020951969790729996
        },
        {
            "time": "2026-04-23T15:55:00+00:00",
            "open": 86.905,
            "high": 86.935,
            "low": 86.875,
            "close": 86.905,
            "volume": 52719.118652,
            "ma20": 86.962375,
            "rsi14": 48.470055386834595,
            "macd": 0.015742565530260322,
            "macd_signal": 0.03646270438955268,
            "macd_hist": -0.02072013885929236
        },
        {
            "time": "2026-04-23T16:00:00+00:00",
            "open": 86.865,
            "high": 86.91,
            "low": 86.865,
            "close": 86.865,
            "volume": 93545.844084,
            "ma20": 86.956875,
            "rsi14": 42.84844362226054,
            "macd": 0.00849548204720918,
            "macd_signal": 0.03086925992108398,
            "macd_hist": -0.0223737778738748
        },
        {
            "time": "2026-04-23T16:05:00+00:00",
            "open": 86.865,
            "high": 86.87,
            "low": 86.85,
            "close": 86.865,
            "volume": 125055.95233900001,
            "ma20": 86.951875,
            "rsi14": 42.84844362226054,
            "macd": 0.00272075302717667,
            "macd_signal": 0.025239558542302518,
            "macd_hist": -0.022518805515125848
        },
        {
            "time": "2026-04-23T16:10:00+00:00",
            "open": 86.86,
            "high": 86.89,
            "low": 86.85,
            "close": 86.86,
            "volume": 20191.835272,
            "ma20": 86.94912500000001,
            "rsi14": 42.13991023568919,
            "macd": -0.0022334734475322193,
            "macd_signal": 0.019744952144335574,
            "macd_hist": -0.021978425591867794
        },
        {
            "time": "2026-04-23T16:15:00+00:00",
            "open": 86.9,
            "high": 86.925,
            "low": 86.86,
            "close": 86.9,
            "volume": 74576.387024,
            "ma20": 86.947875,
            "rsi14": 49.354924017293285,
            "macd": -0.002898654036556536,
            "macd_signal": 0.015216230908157153,
            "macd_hist": -0.018114884944713687
        },
        {
            "time": "2026-04-23T16:20:00+00:00",
            "open": 86.885,
            "high": 86.9,
            "low": 86.87,
            "close": 86.885,
            "volume": 39226.267622,
            "ma20": 86.944125,
            "rsi14": 46.98863990664139,
            "macd": -0.004583355021864577,
            "macd_signal": 0.011256313722152807,
            "macd_hist": -0.015839668744017384
        },
        {
            "time": "2026-04-23T16:25:00+00:00",
            "open": 86.8899,
            "high": 86.905,
            "low": 86.88,
            "close": 86.8899,
            "volume": 22321.579816,
            "ma20": 86.93887,
            "rsi14": 47.86792739924746,
            "macd": -0.0054601622892676005,
            "macd_signal": 0.007913018519868725,
            "macd_hist": -0.013373180809136326
        },
        {
            "time": "2026-04-23T16:30:00+00:00",
            "open": 86.905,
            "high": 86.9118,
            "low": 86.87,
            "close": 86.905,
            "volume": 39654.633308000004,
            "ma20": 86.93387,
            "rsi14": 50.58787792777149,
            "macd": -0.004880337073842611,
            "macd_signal": 0.005354347401126458,
            "macd_hist": -0.010234684474969068
        },
        {
            "time": "2026-04-23T16:35:00+00:00",
            "open": 86.8688,
            "high": 86.92,
            "low": 86.86,
            "close": 86.8688,
            "volume": 68047.094877,
            "ma20": 86.92781,
            "rsi14": 44.582543931368264,
            "macd": -0.0072581909697362335,
            "macd_signal": 0.00283183972695392,
            "macd_hist": -0.010090030696690153
        },
        {
            "time": "2026-04-23T16:40:00+00:00",
            "open": 86.9,
            "high": 86.9,
            "low": 86.865,
            "close": 86.9,
            "volume": 86492.24215900002,
            "ma20": 86.92331,
            "rsi14": 50.08267130990762,
            "macd": -0.006549578597940808,
            "macd_signal": 0.0009555560619749744,
            "macd_hist": -0.007505134659915783
        },
        {
            "time": "2026-04-23T16:45:00+00:00",
            "open": 86.91,
            "high": 86.92,
            "low": 86.8999,
            "close": 86.91,
            "volume": 22808.89229,
            "ma20": 86.92056,
            "rsi14": 51.73607494876545,
            "macd": -0.0051220380946972455,
            "macd_signal": -0.00025996276935946955,
            "macd_hist": -0.004862075325337776
        },
        {
            "time": "2026-04-23T16:50:00+00:00",
            "open": 86.9101,
            "high": 86.925,
            "low": 86.905,
            "close": 86.9101,
            "volume": 34388.227547999995,
            "ma20": 86.91706500000001,
            "rsi14": 51.7532849137116,
            "macd": -0.003937246668002103,
            "macd_signal": -0.0009954195490879964,
            "macd_hist": -0.002941827118914107
        },
        {
            "time": "2026-04-23T16:55:00+00:00",
            "open": 86.885,
            "high": 86.92,
            "low": 86.855,
            "close": 86.885,
            "volume": 33151.516893,
            "ma20": 86.910815,
            "rsi14": 47.203508715956225,
            "macd": -0.004966401571110168,
            "macd_signal": -0.0017896159534924309,
            "macd_hist": -0.0031767856176177374
        },
        {
            "time": "2026-04-23T17:00:00+00:00",
            "open": 86.76,
            "high": 86.895,
            "low": 86.75,
            "close": 86.76,
            "volume": 155801.899729,
            "ma20": 86.898065,
            "rsi14": 32.07870100144905,
            "macd": -0.015687632317735734,
            "macd_signal": -0.004569219226341091,
            "macd_hist": -0.011118413091394642
        },
        {
            "time": "2026-04-23T17:05:00+00:00",
            "open": 86.58,
            "high": 86.77,
            "low": 86.58,
            "close": 86.58,
            "volume": 199460.40017799998,
            "ma20": 86.87681,
            "rsi14": 21.430191745230687,
            "macd": -0.03826765489905881,
            "macd_signal": -0.011308906360884635,
            "macd_hist": -0.026958748538174176
        },
        {
            "time": "2026-04-23T17:10:00+00:00",
            "open": 86.4569,
            "high": 86.57,
            "low": 86.43,
            "close": 86.4569,
            "volume": 787512.531663,
            "ma20": 86.850785,
            "rsi14": 17.22020609753261,
            "macd": -0.06534240017049342,
            "macd_signal": -0.022115605122806394,
            "macd_hist": -0.043226795047687026
        },
        {
            "time": "2026-04-23T17:15:00+00:00",
            "open": 86.33,
            "high": 86.455,
            "low": 86.3201,
            "close": 86.33,
            "volume": 744141.8400980001,
            "ma20": 86.819785,
            "rsi14": 14.137014496343753,
            "macd": -0.09593324162051431,
            "macd_signal": -0.03687913242234798,
            "macd_hist": -0.05905410919816633
        },
        {
            "time": "2026-04-23T17:20:00+00:00",
            "open": 86.305,
            "high": 86.37,
            "low": 86.29,
            "close": 86.305,
            "volume": 442955.00797000004,
            "ma20": 86.78928499999999,
            "rsi14": 13.619656238660554,
            "macd": -0.12080147077232084,
            "macd_signal": -0.053663600092342556,
            "macd_hist": -0.06713787067997828
        },
        {
            "time": "2026-04-23T17:25:00+00:00",
            "open": 86.325,
            "high": 86.4,
            "low": 86.3,
            "close": 86.325,
            "volume": 392811.65842100006,
            "ma20": 86.759285,
            "rsi14": 16.259887048755928,
            "macd": -0.13731302955766012,
            "macd_signal": -0.07039348598540607,
            "macd_hist": -0.06691954357225405
        },
        {
            "time": "2026-04-23T17:30:00+00:00",
            "open": 86.4192,
            "high": 86.4192,
            "low": 86.3,
            "close": 86.4192,
            "volume": 177671.471377,
            "ma20": 86.736245,
            "rsi14": 27.499997497306623,
            "macd": -0.1411700852492146,
            "macd_signal": -0.08454880583816778,
            "macd_hist": -0.05662127941104682
        },
        {
            "time": "2026-04-23T17:35:00+00:00",
            "open": 86.35,
            "high": 86.445,
            "low": 86.3151,
            "close": 86.35,
            "volume": 266836.984189,
            "ma20": 86.708495,
            "rsi14": 24.86014001248556,
            "macd": -0.14810344699903055,
            "macd_signal": -0.09725973407034033,
            "macd_hist": -0.05084371292869022
        },
        {
            "time": "2026-04-23T17:40:00+00:00",
            "open": 86.2899,
            "high": 86.355,
            "low": 86.24,
            "close": 86.2899,
            "volume": 545865.623607,
            "ma20": 86.67974000000001,
            "rsi14": 22.811980053704403,
            "macd": -0.1566420814525884,
            "macd_signal": -0.10913620354678996,
            "macd_hist": -0.04750587790579844
        },
        {
            "time": "2026-04-23T17:45:00+00:00",
            "open": 86.34,
            "high": 86.39,
            "low": 86.245,
            "close": 86.34,
            "volume": 180110.007516,
            "ma20": 86.65349,
            "rsi14": 28.127787632158345,
            "macd": -0.1575502186289981,
            "macd_signal": -0.1188190065632316,
            "macd_hist": -0.03873121206576649
        },
        {
            "time": "2026-04-23T17:50:00+00:00",
            "open": 86.465,
            "high": 86.55,
            "low": 86.31,
            "close": 86.465,
            "volume": 645941.9154399999,
            "ma20": 86.63374,
            "rsi14": 39.35062461441486,
            "macd": -0.14649476805632844,
            "macd_signal": -0.12435415886185099,
            "macd_hist": -0.022140609194477454
        },
        {
            "time": "2026-04-23T17:55:00+00:00",
            "open": 86.59,
            "high": 86.595,
            "low": 86.46,
            "close": 86.59,
            "volume": 362510.917314,
            "ma20": 86.61824,
            "rsi14": 48.0813394604773,
            "macd": -0.12619212423950898,
            "macd_signal": -0.1247217519373826,
            "macd_hist": -0.001470372302126391
        },
        {
            "time": "2026-04-23T18:00:00+00:00",
            "open": 86.6401,
            "high": 86.705,
            "low": 86.585,
            "close": 86.6401,
            "volume": 280944.12342899997,
            "ma20": 86.60599500000001,
            "rsi14": 51.11858324811664,
            "macd": -0.10485082638598442,
            "macd_signal": -0.12074756682710297,
            "macd_hist": 0.01589674044111855
        },
        {
            "time": "2026-04-23T18:05:00+00:00",
            "open": 86.61,
            "high": 86.685,
            "low": 86.61,
            "close": 86.61,
            "volume": 205434.799635,
            "ma20": 86.59200000000001,
            "rsi14": 49.25429222338327,
            "macd": -0.08933669471856831,
            "macd_signal": -0.11446539240539604,
            "macd_hist": 0.025128697686827725
        },
        {
            "time": "2026-04-23T18:10:00+00:00",
            "open": 86.655,
            "high": 86.68,
            "low": 86.61,
            "close": 86.655,
            "volume": 206980.08325899998,
            "ma20": 86.57950000000001,
            "rsi14": 52.06868645720144,
            "macd": -0.0725739226746498,
            "macd_signal": -0.1060870984592468,
            "macd_hist": 0.033513175784597005
        },
        {
            "time": "2026-04-23T18:15:00+00:00",
            "open": 86.6501,
            "high": 86.68,
            "low": 86.6,
            "close": 86.6501,
            "volume": 345067.283072,
            "ma20": 86.568565,
            "rsi14": 51.73224062196268,
            "macd": -0.05900452665534317,
            "macd_signal": -0.09667058409846607,
            "macd_hist": 0.0376660574431229
        },
        {
            "time": "2026-04-23T18:20:00+00:00",
            "open": 86.655,
            "high": 86.675,
            "low": 86.63,
            "close": 86.655,
            "volume": 39696.923009000006,
            "ma20": 86.55631500000001,
            "rsi14": 52.06579660310927,
            "macd": -0.04730993402877459,
            "macd_signal": -0.08679845408452777,
            "macd_hist": 0.03948852005575318
        },
        {
            "time": "2026-04-23T18:25:00+00:00",
            "open": 86.68,
            "high": 86.69,
            "low": 86.64,
            "close": 86.68,
            "volume": 145017.886449,
            "ma20": 86.544815,
            "rsi14": 53.81927707169596,
            "macd": -0.03561405736660106,
            "macd_signal": -0.07656157474094243,
            "macd_hist": 0.040947517374341366
        },
        {
            "time": "2026-04-23T18:30:00+00:00",
            "open": 86.695,
            "high": 86.715,
            "low": 86.68,
            "close": 86.695,
            "volume": 89717.942668,
            "ma20": 86.53406,
            "rsi14": 54.88564267301065,
            "macd": -0.024848181835082528,
            "macd_signal": -0.06621889615977045,
            "macd_hist": 0.04137071432468792
        },
        {
            "time": "2026-04-23T18:35:00+00:00",
            "open": 86.675,
            "high": 86.71,
            "low": 86.645,
            "close": 86.675,
            "volume": 62243.259617,
            "ma20": 86.52356,
            "rsi14": 53.12422861978511,
            "macd": -0.01772565050028163,
            "macd_signal": -0.056520247027872686,
            "macd_hist": 0.038794596527591055
        },
        {
            "time": "2026-04-23T18:40:00+00:00",
            "open": 86.655,
            "high": 86.68,
            "low": 86.59,
            "close": 86.655,
            "volume": 69104.678755,
            "ma20": 86.51831,
            "rsi14": 51.34953297099964,
            "macd": -0.013538759562763403,
            "macd_signal": -0.04792394953485083,
            "macd_hist": 0.03438518997208743
        },
        {
            "time": "2026-04-23T18:45:00+00:00",
            "open": 86.605,
            "high": 86.66,
            "low": 86.605,
            "close": 86.605,
            "volume": 43396.513543999994,
            "ma20": 86.51956,
            "rsi14": 47.11222925261193,
            "macd": -0.014092748035508862,
            "macd_signal": -0.041157709234982444,
            "macd_hist": 0.027064961199473582
        },
        {
            "time": "2026-04-23T18:50:00+00:00",
            "open": 86.65,
            "high": 86.66,
            "low": 86.6,
            "close": 86.65,
            "volume": 112272.40850700001,
            "ma20": 86.529215,
            "rsi14": 51.028925752875786,
            "macd": -0.010776439881269084,
            "macd_signal": -0.035081455364239775,
            "macd_hist": 0.02430501548297069
        },
        {
            "time": "2026-04-23T18:55:00+00:00",
            "open": 86.57,
            "high": 86.655,
            "low": 86.56,
            "close": 86.57,
            "volume": 789565.29386,
            "ma20": 86.541215,
            "rsi14": 44.692281314848756,
            "macd": -0.014437150701951396,
            "macd_signal": -0.0309525944317821,
            "macd_hist": 0.016515443729830704
        },
        {
            "time": "2026-04-23T19:00:00+00:00",
            "open": 86.5,
            "high": 86.61,
            "low": 86.5,
            "close": 86.5,
            "volume": 257019.956368,
            "ma20": 86.55096499999999,
            "rsi14": 40.010514438412635,
            "macd": -0.022724748630380986,
            "macd_signal": -0.02930702527150188,
            "macd_hist": 0.006582276641120894
        },
        {
            "time": "2026-04-23T19:05:00+00:00",
            "open": 86.5597,
            "high": 86.5651,
            "low": 86.48,
            "close": 86.5597,
            "volume": 702736.791792,
            "ma20": 86.56269999999999,
            "rsi14": 45.275752740145855,
            "macd": -0.02419651625373831,
            "macd_signal": -0.02828492346794917,
            "macd_hist": 0.00408840721421086
        },
        {
            "time": "2026-04-23T19:10:00+00:00",
            "open": 86.555,
            "high": 86.565,
            "low": 86.53,
            "close": 86.555,
            "volume": 53229.706934999995,
            "ma20": 86.56949,
            "rsi14": 44.94132906426256,
            "macd": -0.02544879554548629,
            "macd_signal": -0.027717697883456596,
            "macd_hist": 0.0022689023379703042
        },
        {
            "time": "2026-04-23T19:15:00+00:00",
            "open": 86.5499,
            "high": 86.575,
            "low": 86.53,
            "close": 86.5499,
            "volume": 79758.835311,
            "ma20": 86.579485,
            "rsi14": 44.55673577220797,
            "macd": -0.02654674888751174,
            "macd_signal": -0.027483508084267628,
            "macd_hist": 0.0009367591967558882
        },
        {
            "time": "2026-04-23T19:20:00+00:00",
            "open": 86.52,
            "high": 86.5473,
            "low": 86.52,
            "close": 86.52,
            "volume": 92343.672043,
            "ma20": 86.59099,
            "rsi14": 42.272707110115014,
            "macd": -0.029489626874706687,
            "macd_signal": -0.027884731842355442,
            "macd_hist": -0.0016048950323512452
        },
        {
            "time": "2026-04-23T19:25:00+00:00",
            "open": 86.52,
            "high": 86.52,
            "low": 86.4901,
            "close": 86.52,
            "volume": 99586.356114,
            "ma20": 86.59999,
            "rsi14": 42.272707110115014,
            "macd": -0.03145923638747661,
            "macd_signal": -0.028599632751379677,
            "macd_hist": -0.002859603636096931
        },
        {
            "time": "2026-04-23T19:30:00+00:00",
            "open": 86.525,
            "high": 86.565,
            "low": 86.52,
            "close": 86.525,
            "volume": 88100.86162000001,
            "ma20": 86.60299,
            "rsi14": 42.84095953158705,
            "macd": -0.032245007528402425,
            "macd_signal": -0.02932870770678423,
            "macd_hist": -0.0029162998216181943
        },
        {
            "time": "2026-04-23T19:35:00+00:00",
            "open": 86.545,
            "high": 86.565,
            "low": 86.505,
            "close": 86.545,
            "volume": 93990.1442,
            "ma20": 86.60074,
            "rsi14": 45.16612423516908,
            "macd": -0.030897734119960774,
            "macd_signal": -0.029642512989419542,
            "macd_hist": -0.0012552211305412314
        },
        {
            "time": "2026-04-23T19:40:00+00:00",
            "open": 86.55,
            "high": 86.58,
            "low": 86.515,
            "close": 86.55,
            "volume": 204585.593323,
            "ma20": 86.59623500000001,
            "rsi14": 45.76015904028131,
            "macd": -0.029091206701721717,
            "macd_signal": -0.02953225173187998,
            "macd_hist": 0.0004410450301582623
        },
        {
            "time": "2026-04-23T19:45:00+00:00",
            "open": 86.61,
            "high": 86.615,
            "low": 86.545,
            "close": 86.61,
            "volume": 170878.973888,
            "ma20": 86.59623500000001,
            "rsi14": 52.42120346195686,
            "macd": -0.02255798770792694,
            "macd_signal": -0.02813739892708937,
            "macd_hist": 0.005579411219162431
        },
        {
            "time": "2026-04-23T19:50:00+00:00",
            "open": 86.625,
            "high": 86.63,
            "low": 86.565,
            "close": 86.625,
            "volume": 636152.0156149999,
            "ma20": 86.594735,
            "rsi14": 53.943976072027915,
            "macd": -0.015985716556585317,
            "macd_signal": -0.02570706245298856,
            "macd_hist": 0.009721345896403243
        },
        {
            "time": "2026-04-23T19:55:00+00:00",
            "open": 86.57,
            "high": 86.64,
            "low": 86.54,
            "close": 86.57,
            "volume": 2429236.46193,
            "ma20": 86.59073,
            "rsi14": 47.89146193906955,
            "macd": -0.01504179224647828,
            "macd_signal": -0.023574008411686505,
            "macd_hist": 0.008532216165208224
        },
        {
            "time": "2026-04-23T20:00:00+00:00",
            "open": 86.62,
            "high": 86.62,
            "low": 86.53,
            "close": 86.62,
            "volume": 98058.605317,
            "ma20": 86.58898,
            "rsi14": 53.048863695850066,
            "macd": -0.01014222998361447,
            "macd_signal": -0.0208876527260721,
            "macd_hist": 0.010745422742457631
        },
        {
            "time": "2026-04-23T20:05:00+00:00",
            "open": 86.63,
            "high": 86.645,
            "low": 86.6,
            "close": 86.63,
            "volume": 11394.46387,
            "ma20": 86.58648,
            "rsi14": 54.02885467467483,
            "macd": -0.0053902398348384395,
            "macd_signal": -0.01778817014782537,
            "macd_hist": 0.01239793031298693
        },
        {
            "time": "2026-04-23T20:10:00+00:00",
            "open": 86.59,
            "high": 86.63,
            "low": 86.59,
            "close": 86.59,
            "volume": 15194.69072,
            "ma20": 86.58123,
            "rsi14": 49.57173058048,
            "macd": -0.00479662658625557,
            "macd_signal": -0.01518986143551141,
            "macd_hist": 0.01039323484925584
        },
        {
            "time": "2026-04-23T20:15:00+00:00",
            "open": 86.59,
            "high": 86.6,
            "low": 86.57,
            "close": 86.59,
            "volume": 47497,
            "ma20": 86.57698,
            "rsi14": 49.57173058048,
            "macd": -0.004276882569996587,
            "macd_signal": -0.013007265662408446,
            "macd_hist": 0.008730383092411859
        },
        {
            "time": "2026-04-23T20:20:00+00:00",
            "open": 86.59,
            "high": 86.6,
            "low": 86.56,
            "close": 86.59,
            "volume": 82064.057726,
            "ma20": 86.57373,
            "rsi14": 49.57173058048,
            "macd": -0.003820936317140422,
            "macd_signal": -0.011169999793354842,
            "macd_hist": 0.00734906347621442
        },
        {
            "time": "2026-04-23T20:25:00+00:00",
            "open": 86.61,
            "high": 86.61,
            "low": 86.56,
            "close": 86.61,
            "volume": 10483,
            "ma20": 86.57398,
            "rsi14": 52.04237738633333,
            "macd": -0.0018247284402121977,
            "macd_signal": -0.009300945522726313,
            "macd_hist": 0.007476217082514116
        },
        {
            "time": "2026-04-23T20:30:00+00:00",
            "open": 86.6,
            "high": 86.62,
            "low": 86.6,
            "close": 86.6,
            "volume": 1602.478452,
            "ma20": 86.57148,
            "rsi14": 50.70473565005671,
            "macd": -0.001037674081473483,
            "macd_signal": -0.007648291234475748,
            "macd_hist": 0.0066106171530022646
        },
        {
            "time": "2026-04-23T20:35:00+00:00",
            "open": 86.61,
            "high": 86.61,
            "low": 86.61,
            "close": 86.61,
            "volume": 1170,
            "ma20": 86.57347999999999,
            "rsi14": 52.03248050542007,
            "macd": 0.00038851009225027155,
            "macd_signal": -0.006040930969130544,
            "macd_hist": 0.0064294410613808155
        },
        {
            "time": "2026-04-23T20:40:00+00:00",
            "open": 86.65,
            "high": 86.65,
            "low": 86.62,
            "close": 86.65,
            "volume": 4004,
            "ma20": 86.58098,
            "rsi14": 57.019340516124565,
            "macd": 0.004692346580583262,
            "macd_signal": -0.003894275459187783,
            "macd_hist": 0.008586622039771044
        },
        {
            "time": "2026-04-23T20:45:00+00:00",
            "open": 86.66,
            "high": 86.66,
            "low": 86.66,
            "close": 86.66,
            "volume": 125,
            "ma20": 86.585995,
            "rsi14": 58.189617723591354,
            "macd": 0.00880854500783812,
            "macd_signal": -0.0013537113657826024,
            "macd_hist": 0.010162256373620723
        },
        {
            "time": "2026-04-23T20:50:00+00:00",
            "open": 86.66,
            "high": 86.66,
            "low": 86.65,
            "close": 86.66,
            "volume": 1890,
            "ma20": 86.591245,
            "rsi14": 58.189617723591354,
            "macd": 0.01193310451628804,
            "macd_signal": 0.0013036518106315264,
            "macd_hist": 0.010629452705656513
        },
        {
            "time": "2026-04-23T21:10:00+00:00",
            "open": 86.66,
            "high": 86.66,
            "low": 86.65,
            "close": 86.66,
            "volume": 1622,
            "ma20": 86.59675,
            "rsi14": 58.189617723591354,
            "macd": 0.014245131430129732,
            "macd_signal": 0.0038919477345311674,
            "macd_hist": 0.010353183695598563
        },
        {
            "time": "2026-04-23T21:15:00+00:00",
            "open": 86.6339,
            "high": 86.6339,
            "low": 86.6339,
            "close": 86.6339,
            "volume": 718,
            "ma20": 86.602445,
            "rsi14": 53.44584195523209,
            "macd": 0.013812159565702586,
            "macd_signal": 0.005875990100765451,
            "macd_hist": 0.007936169464937136
        }
    ],
    "analysis_parameters": {
        "bucket_width": 0.0693,
        "atr": 0.0372,
        "rows_used": 100
    },
    "volume": {
        "current_bar": 718,
        "expected_bar": null,
        "bar_ratio": null,
        "current_day": 16596511.69,
        "expected_day": null,
        "day_ratio": null
    },
    "source": "massive"
}